{
  "date": "2026-04-29",
  "generated_at": "2026-04-29T12:09:18.894136",
  "today": "2026-04-29",
  "tomorrow": "2026-04-30",
  "games": [
    {
      "id": "Orlando_Magic_vs_Detroit_Pistons_2026-04-29",
      "matchup": "Orlando Magic @ Detroit Pistons",
      "home_team": "Detroit Pistons",
      "away_team": "Orlando Magic",
      "predicted_winner": "Detroit Pistons",
      "predicted_home_prob": 0.6499999999999999,
      "predicted_away_prob": 0.35000000000000003,
      "home_odds": 1.29,
      "away_odds": 2.86,
      "confidence": 0.863281745362195,
      "date": "2026-04-29",
      "published": false
    },
    {
      "id": "Toronto_Raptors_vs_Cleveland_Cavaliers_2026-04-29",
      "matchup": "Toronto Raptors @ Cleveland Cavaliers",
      "home_team": "Cleveland Cavaliers",
      "away_team": "Toronto Raptors",
      "predicted_winner": "Cleveland Cavaliers",
      "predicted_home_prob": 0.6499999999999999,
      "predicted_away_prob": 0.35000000000000003,
      "home_odds": 1.27,
      "away_odds": 2.86,
      "confidence": 0.8479142734886923,
      "date": "2026-04-29",
      "published": false
    },
    {
      "id": "Houston_Rockets_vs_Los_Angeles_Lakers_2026-04-29",
      "matchup": "Houston Rockets @ Los Angeles Lakers",
      "home_team": "Los Angeles Lakers",
      "away_team": "Houston Rockets",
      "predicted_winner": "Houston Rockets",
      "predicted_home_prob": 0.30000000000000004,
      "predicted_away_prob": 0.7,
      "home_odds": 1.67,
      "away_odds": 1.43,
      "confidence": 0.8127177740751008,
      "date": "2026-04-29",
      "published": false
    },
    {
      "id": "New_York_Knicks_vs_Atlanta_Hawks_2026-04-30",
      "matchup": "New York Knicks @ Atlanta Hawks",
      "home_team": "Atlanta Hawks",
      "away_team": "New York Knicks",
      "predicted_winner": "Atlanta Hawks",
      "predicted_home_prob": 0.7,
      "predicted_away_prob": 0.30000000000000004,
      "home_odds": 2.14,
      "away_odds": 3.33,
      "confidence": 0.9006107831061025,
      "date": "2026-04-30",
      "published": false
    },
    {
      "id": "Denver_Nuggets_vs_Minnesota_Timberwolves_2026-04-30",
      "matchup": "Denver Nuggets @ Minnesota Timberwolves",
      "home_team": "Minnesota Timberwolves",
      "away_team": "Denver Nuggets",
      "predicted_winner": "Minnesota Timberwolves",
      "predicted_home_prob": 0.6,
      "predicted_away_prob": 0.4,
      "home_odds": 2.95,
      "away_odds": 2.5,
      "confidence": 0.8597229053936539,
      "date": "2026-04-30",
      "published": false
    },
    {
      "id": "Boston_Celtics_vs_Philadelphia_76ers_2026-04-30",
      "matchup": "Boston Celtics @ Philadelphia 76ers",
      "home_team": "Philadelphia 76ers",
      "away_team": "Boston Celtics",
      "predicted_winner": "Boston Celtics",
      "predicted_home_prob": 0.3898058252427185,
      "predicted_away_prob": 0.6101941747572815,
      "home_odds": 2.85,
      "away_odds": 1.64,
      "confidence": 0.8404903288975766,
      "date": "2026-04-30",
      "published": false
    }
  ],
  "games_today": [
    {
      "id": "Orlando_Magic_vs_Detroit_Pistons_2026-04-29",
      "matchup": "Orlando Magic @ Detroit Pistons",
      "home_team": "Detroit Pistons",
      "away_team": "Orlando Magic",
      "predicted_winner": "Detroit Pistons",
      "predicted_home_prob": 0.6499999999999999,
      "predicted_away_prob": 0.35000000000000003,
      "home_odds": 1.29,
      "away_odds": 2.86,
      "confidence": 0.863281745362195,
      "date": "2026-04-29",
      "published": false
    },
    {
      "id": "Toronto_Raptors_vs_Cleveland_Cavaliers_2026-04-29",
      "matchup": "Toronto Raptors @ Cleveland Cavaliers",
      "home_team": "Cleveland Cavaliers",
      "away_team": "Toronto Raptors",
      "predicted_winner": "Cleveland Cavaliers",
      "predicted_home_prob": 0.6499999999999999,
      "predicted_away_prob": 0.35000000000000003,
      "home_odds": 1.27,
      "away_odds": 2.86,
      "confidence": 0.8479142734886923,
      "date": "2026-04-29",
      "published": false
    },
    {
      "id": "Houston_Rockets_vs_Los_Angeles_Lakers_2026-04-29",
      "matchup": "Houston Rockets @ Los Angeles Lakers",
      "home_team": "Los Angeles Lakers",
      "away_team": "Houston Rockets",
      "predicted_winner": "Houston Rockets",
      "predicted_home_prob": 0.30000000000000004,
      "predicted_away_prob": 0.7,
      "home_odds": 1.67,
      "away_odds": 1.43,
      "confidence": 0.8127177740751008,
      "date": "2026-04-29",
      "published": false
    }
  ],
  "games_tomorrow": [
    {
      "id": "New_York_Knicks_vs_Atlanta_Hawks_2026-04-30",
      "matchup": "New York Knicks @ Atlanta Hawks",
      "home_team": "Atlanta Hawks",
      "away_team": "New York Knicks",
      "predicted_winner": "Atlanta Hawks",
      "predicted_home_prob": 0.7,
      "predicted_away_prob": 0.30000000000000004,
      "home_odds": 2.14,
      "away_odds": 3.33,
      "confidence": 0.9006107831061025,
      "date": "2026-04-30",
      "published": false
    },
    {
      "id": "Denver_Nuggets_vs_Minnesota_Timberwolves_2026-04-30",
      "matchup": "Denver Nuggets @ Minnesota Timberwolves",
      "home_team": "Minnesota Timberwolves",
      "away_team": "Denver Nuggets",
      "predicted_winner": "Minnesota Timberwolves",
      "predicted_home_prob": 0.6,
      "predicted_away_prob": 0.4,
      "home_odds": 2.95,
      "away_odds": 2.5,
      "confidence": 0.8597229053936539,
      "date": "2026-04-30",
      "published": false
    },
    {
      "id": "Boston_Celtics_vs_Philadelphia_76ers_2026-04-30",
      "matchup": "Boston Celtics @ Philadelphia 76ers",
      "home_team": "Philadelphia 76ers",
      "away_team": "Boston Celtics",
      "predicted_winner": "Boston Celtics",
      "predicted_home_prob": 0.3898058252427185,
      "predicted_away_prob": 0.6101941747572815,
      "home_odds": 2.85,
      "away_odds": 1.64,
      "confidence": 0.8404903288975766,
      "date": "2026-04-30",
      "published": false
    }
  ]
}